betterplotlib/__init__.py
betterplotlib/_interface.py
betterplotlib/axes_bpl.py
betterplotlib/colors.py
betterplotlib/manage_axes.py
betterplotlib/styles.py
betterplotlib/tools.py
betterplotlib/type_checking.py
betterplotlib/resources/Lato-Black.ttf
betterplotlib/resources/Lato-BlackItalic.ttf
betterplotlib/resources/Lato-Bold.ttf
betterplotlib/resources/Lato-BoldItalic.ttf
betterplotlib/resources/Lato-ExtraBold.ttf
betterplotlib/resources/Lato-ExtraBoldItalic.ttf
betterplotlib/resources/Lato-ExtraLight.ttf
betterplotlib/resources/Lato-ExtraLightItalic.ttf
betterplotlib/resources/Lato-Italic.ttf
betterplotlib/resources/Lato-Light.ttf
betterplotlib/resources/Lato-LightItalic.ttf
betterplotlib/resources/Lato-Medium.ttf
betterplotlib/resources/Lato-MediumItalic.ttf
betterplotlib/resources/Lato-Regular.ttf
betterplotlib/resources/Lato-SemiBold.ttf
betterplotlib/resources/Lato-SemiBoldItalic.ttf
betterplotlib/resources/Lato-Thin.ttf
betterplotlib/resources/Lato-ThinItalic.ttf
betterplotlib/resources/License-Lato.txt
betterplotlib-1.12.12.dist-info/licenses/LICENSE
betterplotlib-1.12.12.dist-info/METADATA
betterplotlib-1.12.12.dist-info/WHEEL
betterplotlib-1.12.12.dist-info/top_level.txt
betterplotlib-1.12.12.dist-info/RECORD
